kernel_driver/__init__.py
kernel_driver/connect.py
kernel_driver/driver.py
kernel_driver/kernelspec.py
kernel_driver/message.py
kernel_driver/paths.py
kernel_driver-0.0.7.dist-info/LICENSE
kernel_driver-0.0.7.dist-info/METADATA
kernel_driver-0.0.7.dist-info/WHEEL
kernel_driver-0.0.7.dist-info/top_level.txt
kernel_driver-0.0.7.dist-info/RECORD
