Metadata-Version: 2.1
Name: kernel-driver
Version: 0.0.7
Summary: A Jupyter kernel driver
Home-page: https://github.com/davidbrochart/kernel_driver
Author: David Brochart
Author-email: david.brochart@gmail.com
License: MIT
Keywords: jupyter
Platform: Windows
Platform: Linux
Platform: Mac OS X
Requires-Python: >=3.7
Provides-Extra: test
License-File: LICENSE
